<?xml version="1.0" encoding="UTF-8"?>

<beans xmlns="http://www.springframework.org/schema/beans"
       xmlns:xsi="http://www.w3.org/2001/XMLSchema-instance"
       xmlns:aop="http://www.springframework.org/schema/aop"
       xmlns:tx="http://www.springframework.org/schema/tx"
       xmlns:jee="http://www.springframework.org/schema/jee"
       xsi:schemaLocation="
       http://www.springframework.org/schema/beans http://www.springframework.org/schema/beans/spring-beans-2.0.xsd
       http://www.springframework.org/schema/tx http://www.springframework.org/schema/tx/spring-tx-2.0.xsd
       http://www.springframework.org/schema/aop http://www.springframework.org/schema/aop/spring-aop-2.0.xsd
       http://www.springframework.org/schema/jee http://www.springframework.org/schema/jee/spring-jee-2.0.xsd">
	
	<bean id="defaultJmsService" class="com.consol.citrus.service.JmsService" abstract="true">
		<property name="jmsTemplate">
			<bean class="org.springframework.jms.core.JmsTemplate">
			     <property name="connectionFactory" ref="defaultJmsConnectionFactory" />
                 <property name="receiveTimeout" value="${jms.reveiveTimeout}"/>
			</bean>
		</property>
	</bean>
	
	<bean name="defaultJmsConnectionFactory" class="org.apache.activemq.ActiveMQConnectionFactory">
        <property name="brokerURL" value="tcp://localhost:61616" />
	</bean>	
  
    <bean id="purgeJmsQueues" class="com.consol.citrus.actions.PurgeJmsQueuesBean">
        <property name="queueConnectionFactory">
            <ref bean="defaultJmsConnectionFactory"></ref>
        </property>
        <property name="queueNames">
            <list>
                <value>${travel.agency.request.queue}</value>
                <value>${travel.agency.response.queue}</value>
                <value>${smart.airline.request.queue}</value>
                <value>${smart.airline.response.queue}</value>
                <value>${royal.airline.request.queue}</value>
                <value>${royal.airline.response.queue}</value>
            </list>
        </property>
    </bean>
    	
</beans>
